HISTORY.txt
LICENSE.txt
MANIFEST.in
README.rst
setup.py
version.txt
rst2rst/__init__.py
rst2rst/writer.py
rst2rst.egg-info/PKG-INFO
rst2rst.egg-info/SOURCES.txt
rst2rst.egg-info/dependency_links.txt
rst2rst.egg-info/entry_points.txt
rst2rst.egg-info/not-zip-safe
rst2rst.egg-info/requires.txt
rst2rst.egg-info/top_level.txt
rst2rst/scripts/__init__.py
rst2rst/scripts/rst2rst.py
rst2rst/tests/__init__.py
rst2rst/tests/fixtures/sections-input.txt
rst2rst/tests/fixtures/sections-output.txt