Metadata-Version: 1.0
Name: rst2rst
Version: 0.2
Summary: Transform reStructuredText documents. Standardize RST syntax
Home-page: https://github.com/benoitbryon/rst2rst
Author: Benoit Bryon
Author-email: benoit@marmelune.net
License: BSD
Keywords: rst writer reStructuredText
Platform: UNKNOWN
Classifier: Development Status :: 3 - Alpha
Classifier: License :: OSI Approved :: BSD License
Classifier: Programming Language :: Python :: 2.7
Classifier: Topic :: Documentation
Classifier: Topic :: Software Development :: Documentation
Classifier: Topic :: Software Development :: Quality Assurance
Classifier: Topic :: Text Processing
